osa_differ/__init__.py
osa_differ/exceptions.py
osa_differ/osa_differ.py
osa_differ/templates/offline-header.j2
osa_differ/templates/offline-repo-changes-table.j2
osa_differ/templates/offline-repo-changes.j2
osa_differ-0.3.10.dist-info/LICENSE
osa_differ-0.3.10.dist-info/METADATA
osa_differ-0.3.10.dist-info/WHEEL
osa_differ-0.3.10.dist-info/entry_points.txt
osa_differ-0.3.10.dist-info/top_level.txt
osa_differ-0.3.10.dist-info/RECORD
